sage_wheels/share/reflexive_polytopes/reflexive_polytopes_2d
sage_wheels/share/reflexive_polytopes/reflexive_polytopes_3d
sage_wheels/share/reflexive_polytopes/Full2d/zzdb.info
sage_wheels/share/reflexive_polytopes/Full2d/zzdb.v06
sage_wheels/share/reflexive_polytopes/Full2d/zzdb.v05
sage_wheels/share/reflexive_polytopes/Full2d/zzdb.v03
sage_wheels/share/reflexive_polytopes/Full2d/zzdb.v04
sage_wheels/share/reflexive_polytopes/Full3d/zzdb.v13
sage_wheels/share/reflexive_polytopes/Full3d/zzdb.v12
sage_wheels/share/reflexive_polytopes/Full3d/zzdb.info
sage_wheels/share/reflexive_polytopes/Full3d/zzdb.v06
sage_wheels/share/reflexive_polytopes/Full3d/zzdb.v08
sage_wheels/share/reflexive_polytopes/Full3d/zzdb.v09
sage_wheels/share/reflexive_polytopes/Full3d/zzdb.v07
sage_wheels/share/reflexive_polytopes/Full3d/zzdb.v10
sage_wheels/share/reflexive_polytopes/Full3d/zzdb.v11
sage_wheels/share/reflexive_polytopes/Full3d/zzdb.v05
sage_wheels/share/reflexive_polytopes/Full3d/zzdb.v04
passagemath_polyhedra/__init__.py
passagemath_polyhedra/.dylibs/libgmp.10.dylib
passagemath_polyhedra-10.6.43.dist-info/RECORD
passagemath_polyhedra-10.6.43.dist-info/METADATA.bak
passagemath_polyhedra-10.6.43.dist-info/WHEEL
passagemath_polyhedra-10.6.43.dist-info/top_level.txt
passagemath_polyhedra-10.6.43.dist-info/METADATA
sage/all__sagemath_polyhedra.py
sage/schemes/all__sagemath_polyhedra.py
sage/schemes/toric/fano_variety.py
sage/schemes/toric/divisor_class.pyx
sage/schemes/toric/points.py
sage/schemes/toric/library.py
sage/schemes/toric/toric_subscheme.py
sage/schemes/toric/variety.py
sage/schemes/toric/divisor.py
sage/schemes/toric/weierstrass.py
sage/schemes/toric/divisor_class.cpython-310-darwin.so
sage/schemes/toric/ideal.py
sage/schemes/toric/weierstrass_covering.py
sage/schemes/toric/all.py
sage/schemes/toric/weierstrass_higher.py
sage/schemes/toric/chow_group.py
sage/schemes/toric/homset.py
sage/schemes/toric/morphism.py
sage/schemes/toric/sheaf/klyachko.py
sage/schemes/toric/sheaf/constructor.py
sage/schemes/toric/sheaf/all.py
sage/numerical/mip.pxd
sage/numerical/linear_tensor_constraints.py
sage/numerical/linear_tensor_element.pyx
sage/numerical/linear_functions.pxd
