Metadata-Version: 2.4
Name: passagemath-polyhedra
Version: 10.6.43
Summary: passagemath: Convex polyhedra in arbitrary dimension, mixed integer linear optimization
Author-email: The Sage Developers <sage-support@googlegroups.com>
Maintainer: Matthias Köppe, passagemath contributors
License-Expression: GPL-2.0-or-later
Project-URL: release notes, https://github.com/passagemath/passagemath/releases
Project-URL: repo (upstream), https://github.com/sagemath/sage
Project-URL: repo, https://github.com/passagemath/passagemath
Project-URL: documentation, https://passagemath.org/docs/latest
Project-URL: homepage (upstream), https://www.sagemath.org
Project-URL: discourse, https://passagemath.discourse.group
Project-URL: tracker (upstream), https://github.com/sagemath/sage/issues
Project-URL: tracker, https://github.com/passagemath/passagemath/issues
Classifier: Development Status :: 6 - Mature
Classifier: Intended Audience :: Education
Classifier: Intended Audience :: Science/Research
Classifier: Operating System :: POSIX
Classifier: Operating System :: POSIX :: Linux
Classifier: Operating System :: MacOS :: MacOS X
Classifier: Programming Language :: Python :: 3 :: Only
Classifier: Programming Language :: Python :: 3.10
Classifier: Programming Language :: Python :: 3.11
Classifier: Programming Language :: Python :: 3.12
Classifier: Programming Language :: Python :: 3.13
Classifier: Programming Language :: Python :: 3.14
Classifier: Programming Language :: Python :: Implementation :: CPython
Classifier: Topic :: Scientific/Engineering :: Mathematics
Requires-Python: <3.15,>=3.10
Requires-Dist: gmpy2~=2.1.b999
Requires-Dist: cysignals!=1.12.4; sys_platform == "win32"
Requires-Dist: cysignals!=1.12.0,>=1.11.2
Requires-Dist: passagemath-ppl
Requires-Dist: memory_allocator
Requires-Dist: passagemath-environment~=10.6.43.0
Requires-Dist: passagemath-glpk~=10.6.43.0
Requires-Dist: passagemath-modules~=10.6.43.0
Provides-Extra: conf
Provides-Extra: test
Requires-Dist: passagemath-repl; extra == "test"
Provides-Extra: flint
Requires-Dist: passagemath-flint; extra == "flint"
Provides-Extra: fpylll
Requires-Dist: fpylll>=0.5.9; extra == "fpylll"
Provides-Extra: linbox
Requires-Dist: passagemath-linbox; extra == "linbox"
Provides-Extra: pari
Requires-Dist: passagemath-pari; extra == "pari"
Provides-Extra: 4ti2
Requires-Dist: passagemath-latte-4ti2; extra == "4ti2"
Provides-Extra: cddlib
Requires-Dist: passagemath-cddlib; extra == "cddlib"
Provides-Extra: latte
Requires-Dist: passagemath-polyhedra[latte_int]; extra == "latte"
Provides-Extra: latte-int
Requires-Dist: passagemath-latte-4ti2; extra == "latte-int"
Provides-Extra: normaliz
Requires-Dist: pynormaliz==2.21; extra == "normaliz"
Provides-Extra: palp
Requires-Dist: passagemath-palp; extra == "palp"
Provides-Extra: polymake
Requires-Dist: jupymake>=0.9; extra == "polymake"
Provides-Extra: ppl
Provides-Extra: topcom
Requires-Dist: passagemath-topcom; extra == "topcom"
Provides-Extra: cbc
Requires-Dist: passagemath-polyhedra[cbc_sage]; extra == "cbc"
Provides-Extra: cbc-sage
Requires-Dist: passagemath-coin-or-cbc; extra == "cbc-sage"
Provides-Extra: coin
Requires-Dist: passagemath-polyhedra[cbc_sage]; extra == "coin"
Provides-Extra: coin-sage
Requires-Dist: passagemath-polyhedra[cbc_sage]; extra == "coin-sage"
Provides-Extra: cplex
Requires-Dist: passagemath-polyhedra[cplex_sage]; extra == "cplex"
Provides-Extra: cplex-sage
Requires-Dist: passagemath-cplex; extra == "cplex-sage"
Provides-Extra: cvxopt
Requires-Dist: passagemath-polyhedra[cvxopt_sage]; extra == "cvxopt"
Provides-Extra: cvxopt-sage
Requires-Dist: cvxopt>=1.2.5; extra == "cvxopt-sage"
Provides-Extra: cvxpy
Requires-Dist: cvxpy; extra == "cvxpy"
Provides-Extra: glpk
Requires-Dist: passagemath-polyhedra[glpk_sage]; extra == "glpk"
Provides-Extra: glpk-sage
Provides-Extra: gurobi
Requires-Dist: passagemath-polyhedra[gurobi_sage]; extra == "gurobi"
Provides-Extra: gurobi-sage
Requires-Dist: passagemath-gurobi; extra == "gurobi-sage"
Provides-Extra: scip
Requires-Dist: PySCIPOpt; extra == "scip"
Provides-Extra: polytopes-db-4d
Requires-Dist: passagemath-polytopes-db-4d; extra == "polytopes-db-4d"
Provides-Extra: qq
Provides-Extra: zz
Provides-Extra: rdf
Requires-Dist: passagemath-polyhedra[cddlib]; extra == "rdf"
Provides-Extra: numberfield
Requires-Dist: passagemath-polyhedra[flint]; extra == "numberfield"
Provides-Extra: databases
Requires-Dist: passagemath-polyhedra[polytopes-db-4d]; extra == "databases"
Provides-Extra: graphs
Requires-Dist: passagemath-graphs; extra == "graphs"
Provides-Extra: groups
Requires-Dist: passagemath-groups; extra == "groups"
Provides-Extra: plot
Requires-Dist: passagemath-plot; extra == "plot"
Provides-Extra: standard
Requires-Dist: passagemath-polyhedra[RDF,flint,fpylll,glpk,graphs,groups,linbox,pari]; extra == "standard"
Requires-Dist: passagemath-plot[tachyon]; extra == "standard"
